aws_static_site_deployer/__init__.py
aws_static_site_deployer/cli.py
aws_static_site_deployer/main.py
aws_static_site_deployer/helpers/__init__.py
aws_static_site_deployer/helpers/aws_helpers.py
aws_static_site_deployer/helpers/file_helpers.py
aws_static_site_deployer/helpers/git_helpers.py
aws_static_site_deployer/helpers/logger.py
aws_static_site_deployer/helpers/template_helpers.py
aws_static_site_deployer-0.1.4.dist-info/METADATA
aws_static_site_deployer-0.1.4.dist-info/WHEEL
aws_static_site_deployer-0.1.4.dist-info/entry_points.txt
aws_static_site_deployer-0.1.4.dist-info/top_level.txt
aws_static_site_deployer-0.1.4.dist-info/RECORD
